aibo/__init__.py
aibo/conftest.py
aibo/__db_migrations/env.py
aibo/__db_migrations/versions/112ef53baf2c_add_images_table.py
aibo/__db_migrations/versions/5a31b5a3f565_create_chat_tables.py
aibo/__db_migrations/versions/8c2aa3d4c59a_add_conversation_foreign_keys.py
aibo/__db_migrations/versions/f43a2b565df6_add_fts5.py
aibo/cli/__init__.py
aibo/cli/common.py
aibo/cli/format.py
aibo/cli/migrate.py
aibo/cli/start.py
aibo/cli/test.py
aibo/common/__init__.py
aibo/common/classproperty.py
aibo/common/constants.py
aibo/common/openai.py
aibo/common/result.py
aibo/common/shell.py
aibo/common/shorthands.py
aibo/common/time.py
aibo/common/types.py
aibo/common/utils.py
aibo/common/vector_db.py
aibo/common/chat/__init__.py
aibo/common/chat/message_content.py
aibo/common/chat/message_role.py
aibo/common/chat/message_source.py
aibo/common/tests/test_vector_db.py
aibo/core/__init__.py
aibo/core/chat.py
aibo/core/openai.py
aibo/core/package.py
aibo/core/tests/test_chat.py
aibo/core/tests/test_package.py
aibo/db/__init__.py
aibo/db/client.py
aibo/db/models/__init__.py
aibo/db/models/base_db_model.py
aibo/db/models/conversation_model.py
aibo/db/models/custom_types.py
aibo/db/models/image_model.py
aibo/db/models/message_model.py
aibo/db/models/tests/test_models.py
aibo/packages/__init__.py
aibo/packages/typed_outputs.py
aibo/server/__init__.py
aibo/server/main.py
aibo/server/routes/__init__.py
aibo/server/routes/api_models.py
aibo/server/routes/chat_routes.py
aibo/server/routes/healthcheck_routes.py
aibo/server/routes/image_routes.py
aibo/server/routes/types.py
aibo/server/routes/websocket_route.py
aibo/server/routes/websocket_routes.py
aibo/testing/__init__.py
aibo/testing/factory.py
aibo/testing/factories/__init__.py
aibo/testing/factories/base_factory.py
aibo/testing/factories/chat_factory.py
aibo/testing/factories/model_factory.py
aibo/tools/lang/python.py
aibo/tools/lsp/lsp_server.py
aibo/tools/lsp/lsp_service.py
aibo/tools/lsp/pipe_comms.py
aibo/tools/lsp/utils.py
aibo_server-0.1.7.dist-info/METADATA
aibo_server-0.1.7.dist-info/WHEEL
aibo_server-0.1.7.dist-info/top_level.txt
aibo_server-0.1.7.dist-info/RECORD
